pymyplot/__init__.py
pymyplot/aip.py
pymyplot/basic.py
pymyplot/colors.py
pymyplot/elsevier.py
pymyplot/figsize.py
pymyplot/fonts.py
pymyplot/lines.py
pymyplot/markers.py
pymyplot/scaling.py
pymyplot-0.2.7.dist-info/WHEEL
pymyplot-0.2.7.dist-info/METADATA
pymyplot-0.2.7.dist-info/RECORD
