Metadata-Version: 2.1
Name: pymyplot
Version: 0.2.7
Summary: Correction of usefull plotting setup for matplotlib
Author: Kyoungseoun Chung
Author-email: kchung@student.ethz.ch
Requires-Python: >=3.9,<4.0
Classifier: Programming Language :: Python :: 3
Classifier: Programming Language :: Python :: 3.9
Classifier: Programming Language :: Python :: 3.10
Requires-Dist: matplotlib (>=3.6.0,<4.0.0)
